README.md
setup.py
geospatial_pipelines.egg-info/PKG-INFO
geospatial_pipelines.egg-info/SOURCES.txt
geospatial_pipelines.egg-info/dependency_links.txt
geospatial_pipelines.egg-info/top_level.txt
pdal/__init__.py
pdal/pipeline_generation.py
test/__init__.py